Metadata-Version: 2.1
Name: xmailer
Version: 0.1a2
Summary: Easy to send mail with xmailer!
Author-email: walldevnewthon@gmail.com
